impy/__init__.py
impy/__main__.py
impy/_const.py
impy/_types.py
impy/array_api.py
impy/binder.py
impy/collections.py
impy/core.py
impy/correlation.py
impy/random.py
impy/roi.py
impy/arrays/__init__.py
impy/arrays/_imshow.py
impy/arrays/axesmixin.py
impy/arrays/big.py
impy/arrays/imgarray.py
impy/arrays/label.py
impy/arrays/labeledarray.py
impy/arrays/lazy.py
impy/arrays/phasearray.py
impy/arrays/specials.py
impy/arrays/tiled.py
impy/arrays/_utils/__init__.py
impy/arrays/_utils/_corr.py
impy/arrays/_utils/_deconv.py
impy/arrays/_utils/_docs.py
impy/arrays/_utils/_filters.py
impy/arrays/_utils/_glcm.py
impy/arrays/_utils/_linalg.py
impy/arrays/_utils/_misc.py
impy/arrays/_utils/_plot.py
impy/arrays/_utils/_process_numba.py
impy/arrays/_utils/_skimage.py
impy/arrays/_utils/_structures.py
impy/arrays/_utils/_transform.py
impy/arrays/bases/__init__.py
impy/arrays/bases/metaarray.py
impy/arrays/bases/overload.py
impy/axes/__init__.py
impy/axes/_axes.py
impy/axes/_axes_tuple.py
impy/axes/_axis.py
impy/axes/_slicer.py
impy/frame/__init__.py
impy/frame/frames.py
impy/io/__init__.py
impy/io/_czi.py
impy/io/_mrc.py
impy/io/_nd2.py
impy/io/_npy.py
impy/io/_registry.py
impy/io/_tiff.py
impy/io/_utils.py
impy/io/_zarr.py
impy/lazy/__init__.py
impy/lazy/core.py
impy/lazy/random.py
impy/utils/__init__.py
impy/utils/axesop.py
impy/utils/deco.py
impy/utils/gauss.py
impy/utils/misc.py
impy/utils/slicer.py
impy/utils/utilcls.py
impy/viewer/__init__.py
impy/viewer/utils.py
impy/viewer/viewer.py
impy_array-2.5.1.dist-info/METADATA
impy_array-2.5.1.dist-info/WHEEL
impy_array-2.5.1.dist-info/entry_points.txt
impy_array-2.5.1.dist-info/licenses/LICENSE
impy_array-2.5.1.dist-info/RECORD
