Metadata-Version: 2.4
Name: impy-array
Version: 2.5.1
Summary: Speed up coding/extending image analysis in Python.
Project-URL: Download, https://github.com/hanjinliu/impy
Author-email: Hanjin Liu <liuhanjin-sc@g.ecc.u-tokyo.ac.jp>
License: BSD 3-Clause License
License-File: LICENSE
Classifier: Programming Language :: Python :: 3 :: Only
Classifier: Programming Language :: Python :: 3.9
Classifier: Programming Language :: Python :: 3.10
Classifier: Programming Language :: Python :: 3.11
Classifier: Programming Language :: Python :: 3.12
Classifier: Programming Language :: Python :: 3.13
Classifier: Programming Language :: Python :: Implementation :: CPython
Classifier: Programming Language :: Python :: Implementation :: PyPy
Requires-Python: >=3.9
Requires-Dist: dask>=2021.6.0
Requires-Dist: numpy>=1.22
Requires-Dist: pandas>=1.3
Requires-Dist: scikit-image>=0.20.0
Requires-Dist: scipy>=1.7
Provides-Extra: all
Requires-Dist: mrcfile; extra == 'all'
Requires-Dist: napari>=0.4.17; extra == 'all'
Requires-Dist: roifile; extra == 'all'
Requires-Dist: tifffile; extra == 'all'
Requires-Dist: zarr; extra == 'all'
Provides-Extra: mrc
Requires-Dist: mrcfile; extra == 'mrc'
Provides-Extra: napari
Requires-Dist: napari>=0.4.17; extra == 'napari'
Provides-Extra: testing
Requires-Dist: dask-image; extra == 'testing'
Requires-Dist: mrcfile; extra == 'testing'
Requires-Dist: pytest; extra == 'testing'
Requires-Dist: roifile; extra == 'testing'
Requires-Dist: tifffile; extra == 'testing'
Requires-Dist: zarr; extra == 'testing'
Provides-Extra: tiff
Requires-Dist: tifffile; extra == 'tiff'
Provides-Extra: zarr
Requires-Dist: zarr; extra == 'zarr'
